ibis_ml/__init__.py
ibis_ml/core.py
ibis_ml/metrics.py
ibis_ml/select.py
ibis_ml/steps/__init__.py
ibis_ml/steps/_common.py
ibis_ml/steps/_discretize.py
ibis_ml/steps/_encode.py
ibis_ml/steps/_generate_features.py
ibis_ml/steps/_handle_outliers.py
ibis_ml/steps/_impute.py
ibis_ml/steps/_select_features.py
ibis_ml/steps/_standardize.py
ibis_ml/steps/_temporal.py
ibis_ml/utils/__init__.py
ibis_ml/utils/_pprint.py
ibis_ml/utils/_split.py
ibis_ml-0.1.4.dist-info/licenses/LICENSE
ibis_ml-0.1.4.dist-info/WHEEL
ibis_ml-0.1.4.dist-info/METADATA
ibis_ml-0.1.4.dist-info/RECORD
