Metadata-Version: 2.4
Name: ibis-ml
Version: 0.1.4
Summary: IbisML is a library for building scalable ML pipelines using Ibis.
Author-email: Ibis Maintainers <maintainers@ibis-project.org>
Requires-Python: >=3.10
Classifier: License :: OSI Approved :: Apache Software License
License-File: LICENSE
Requires-Dist: ibis-framework
Requires-Dist: dask[dataframe] ; extra == "dask"
Requires-Dist: ibis-framework[duckdb, examples] ; extra == "dev"
Requires-Dist: polars ; extra == "dev"
Requires-Dist: pytest ; extra == "dev"
Requires-Dist: pytest-cov ; extra == "dev"
Requires-Dist: scikit-learn ; extra == "dev"
Requires-Dist: skorch ; extra == "dev"
Requires-Dist: torch ; extra == "dev"
Requires-Dist: xgboost ; extra == "dev"
Requires-Dist: clickhouse-connect ; extra == "doc"
Requires-Dist: ibis-framework[bigquery, clickhouse, dask, datafusion, druid, duckdb, examples, exasol, flink, impala, mssql, mysql, oracle, pandas, polars, postgres, pyspark, risingwave, snowflake, sqlite, trino] >=9.1 ; extra == "doc"
Requires-Dist: itables ; extra == "doc"
Requires-Dist: jupyter ; extra == "doc"
Requires-Dist: quartodoc ; extra == "doc"
Requires-Dist: scikit-learn<1.6.0 ; extra == "doc"
Requires-Dist: skorch ; extra == "doc"
Requires-Dist: torch ; extra == "doc"
Requires-Dist: xgboost ; extra == "doc"
Project-URL: Home, https://ibis-project.github.io/ibis-ml/
Provides-Extra: dask
Provides-Extra: dev
Provides-Extra: doc
